trackc/__init__.py
trackc/_utils.py
trackc/gs.py
trackc/pa/__init__.py
trackc/pa/cmaps.py
trackc/pa/palettes.py
trackc/pl/Virtual4C.py
trackc/pl/__init__.py
trackc/pl/bed.py
trackc/pl/bedgraph_matrix.py
trackc/pl/bigwig.py
trackc/pl/gene.py
trackc/pl/links.py
trackc/pl/mapc.py
trackc/pl/mapc_markline.py
trackc/pl/mapc_xylim.txt
trackc/pl/scale.py
trackc/pl/vhighlight.py
trackc/pl/zoomin.py
trackc/scripts/__init__.py
trackc/scripts/cli.py
trackc/scripts/gtf2bed12.py
trackc/scripts/tadscore.py
trackc/scripts/trackc_cli.py
trackc/tl/__init__.py
trackc/tl/_getRegionsCmat.py
trackc-0.0.23.dist-info/METADATA
trackc-0.0.23.dist-info/WHEEL
trackc-0.0.23.dist-info/entry_points.txt
trackc-0.0.23.dist-info/licenses/LICENSE
trackc-0.0.23.dist-info/RECORD
