Metadata-Version: 2.4
Name: trackc
Version: 0.0.23
Summary: 
License-File: LICENSE
Author: seqyuan
Author-email: ahworld07@gmail.com
Requires-Python: >=3.8.1
Classifier: Programming Language :: Python :: 3
Classifier: Programming Language :: Python :: 3.9
Classifier: Programming Language :: Python :: 3.10
Classifier: Programming Language :: Python :: 3.11
Classifier: Programming Language :: Python :: 3.12
Classifier: Programming Language :: Python :: 3.13
Classifier: Programming Language :: Python :: 3.14
Requires-Dist: bioframe (>=0.3.3)
Requires-Dist: click (>=7.1.2)
Requires-Dist: colorlog (>=6.7.0,<7.0.0)
Requires-Dist: cooler (>=0.9.1)
Requires-Dist: matplotlib (>=3.6.2)
Requires-Dist: numpy (>=1.23.5)
Requires-Dist: pandas (>=1.5.3)
Requires-Dist: pybigwig (>=0.3.18)
Requires-Dist: seaborn (>=0.12.2)
Requires-Dist: sphinx-gallery (>=0.15.0,<0.16.0)
Project-URL: Homepage, http://trackc.readthedocs.io
Project-URL: Repository, https://github.com/seqyuan/trackc
